basicExample/__init__.py
basicExample/hello.py
BasicExample51-1.0.0.dist-info/METADATA
BasicExample51-1.0.0.dist-info/WHEEL
BasicExample51-1.0.0.dist-info/top_level.txt
BasicExample51-1.0.0.dist-info/RECORD
